guryansh_topsis/__init__.py
guryansh_topsis/__main__.py
guryansh_topsis/topsis.py
Topsis_Guryansh_102218044-1.0.5.dist-info/LICENSE
Topsis_Guryansh_102218044-1.0.5.dist-info/METADATA
Topsis_Guryansh_102218044-1.0.5.dist-info/WHEEL
Topsis_Guryansh_102218044-1.0.5.dist-info/entry_points.txt
Topsis_Guryansh_102218044-1.0.5.dist-info/top_level.txt
Topsis_Guryansh_102218044-1.0.5.dist-info/RECORD
