Metadata-Version: 2.1
Name: Topsis-Guryansh-102218044
Version: 1.0.5
Summary: Python package for Topsis Analysis
Home-page: https://github.com/Guryansh/topsis
Author: Guryansh
Author-email: guryanshsingla@gmail.com
License: MIT
Classifier: License :: OSI Approved :: MIT License
Classifier: Programming Language :: Python :: 3
Classifier: Programming Language :: Python :: 3.6
Classifier: Programming Language :: Python :: 3.7
Classifier: Programming Language :: Python :: 3.8
Classifier: Programming Language :: Python :: 3.9
License-File: LICENSE
Requires-Dist: argparse
Requires-Dist: pandas
Requires-Dist: numpy
